{
    "0x8A779706DA5CA3DD": {
        "name": "_SET_VEHICLE_WEAPON_RELOAD_MODE",
        "comment": "Enables/disables reload behavior for vehicle-mounted **cannons**.\nWhen noReload is true, the cannon fires without requiring a reload; when false, it must reload after shots.\nSupported vehicles only:**breach_cannon** and **hotchkiss_cannon**",
        "params": [
            {
                "type": "Vehicle",
                "name": "vehicle"
            },
            {
                "type": "BOOL",
                "name": "noReload"
            },
            {
                "type": "int",
                "name": "p2"
            }
        ],
        "return_type": "void",
        "build": "1207",
        "examples": [],
        "apiset": ""
    }
}