{
    "0x12FB95FE3D579238": {
        "name": "SET_CURRENT_PED_WEAPON_BY_GUID",
        "comment": "Equips a weapon from a weaponItem, similar to GIVE_WEAPON_TO_PED",
        "params": [
            {
                "type": "Ped",
                "name": "ped"
            },
            {
                "type": "Any*",
                "name": "weaponUid"
            },
            {
                "type": "BOOL",
                "name": "p2"
            },
            {
                "type": "BOOL",
                "name": "p3"
            },
            {
                "type": "BOOL",
                "name": "p4"
            },
            {
                "type": "BOOL",
                "name": "p5"
            }
        ],
        "return_type": "void",
        "build": "1207"
    }
}