{
    "0x9AB33CB5834885B3": {
        "name": "_0x9AB33CB5834885B3",
        "comment": "_SET_PED_M*",
        "params": [
            {
                "type": "Ped",
                "name": "ped"
            },
            {
                "type": "float",
                "name": "p1"
            },
            {
                "type": "float",
                "name": "p2"
            },
            {
                "type": "float",
                "name": "p3"
            },
            {
                "type": "float",
                "name": "p4"
            }
        ],
        "return_type": "void",
        "build": "1207"
    }
}