{
    "0x0522D4774B82E3E6": {
        "name": "CREATE_VOLUME_CYLINDER",
        "comment": "",
        "params": [
            {
                "type": "float",
                "name": "x"
            },
            {
                "type": "float",
                "name": "y"
            },
            {
                "type": "float",
                "name": "z"
            },
            {
                "type": "float",
                "name": "rotX"
            },
            {
                "type": "float",
                "name": "rotY"
            },
            {
                "type": "float",
                "name": "rotZ"
            },
            {
                "type": "float",
                "name": "scaleX"
            },
            {
                "type": "float",
                "name": "scaleY"
            },
            {
                "type": "float",
                "name": "scaleZ"
            }
        ],
        "return_type": "Volume",
        "build": "1207"
    }
}