{
    "0xAD67214236AB1CFE": {
        "name": "TASK_PLAY_UPPER_ANIM_FACING_ENTITY",
        "comment": "",
        "params": [
            {
                "type": "Ped",
                "name": "ped"
            },
            {
                "type": "const char*",
                "name": "animDict"
            },
            {
                "type": "const char*",
                "name": "animName"
            },
            {
                "type": "Entity",
                "name": "entity"
            },
            {
                "type": "int",
                "name": "p4"
            },
            {
                "type": "float",
                "name": "p5"
            },
            {
                "type": "float",
                "name": "p6"
            },
            {
                "type": "int",
                "name": "p7"
            },
            {
                "type": "float",
                "name": "p8"
            },
            {
                "type": "BOOL",
                "name": "p9"
            },
            {
                "type": "BOOL",
                "name": "p10"
            },
            {
                "type": "float",
                "name": "p11"
            },
            {
                "type": "const char*",
                "name": "p12"
            },
            {
                "type": "int",
                "name": "p13"
            },
            {
                "type": "float",
                "name": "p14"
            }
        ],
        "return_type": "void",
        "build": "1207"
    }
}